sdk/__init__.py
zkagi_sdk-0.1.0.dist-info/METADATA
zkagi_sdk-0.1.0.dist-info/WHEEL
zkagi_sdk-0.1.0.dist-info/RECORD
